tez/__init__.py
tez/cli.py
tez/colored_print.py
tez/config.py
tez/genete_example.py
tez/handlers.py
tez/schemas.py
tez/server_session.py
tez_control-1.0.8.dist-info/licenses/LICENCE
tez_control-1.0.8.dist-info/METADATA
tez_control-1.0.8.dist-info/WHEEL
tez_control-1.0.8.dist-info/entry_points.txt
tez_control-1.0.8.dist-info/top_level.txt
tez_control-1.0.8.dist-info/RECORD
