Metadata-Version: 2.4
Name: tez_control
Version: 1.0.8
Summary: A command-line tool for controlling the Tez project
Author-email: dev-au <devaubusiness@gmail.com>
Classifier: Programming Language :: Python :: 3
Classifier: License :: OSI Approved :: MIT License
Classifier: Operating System :: OS Independent
Requires-Python: >=3.8
License-File: LICENCE
Requires-Dist: termcolor==2.5.0
Requires-Dist: pyfiglet==1.0.2
Requires-Dist: fabric==3.2.2
Requires-Dist: invoke==2.2.0
Dynamic: license-file
